esai/__init__.py
esai/api/__init__.py
esai/api/application.py
esai/api/extension.py
esai/api/routers/__init__.py
esai/api/routers/embeddings.py
esai/api/routers/tabular.py
esai/api/routers/textractor.py
esai/app/__init__.py
esai/app/base.py
esai/pipeline/__init__.py
esai/pipeline/base.py
esai/pipeline/factory.py
esai/pipeline/data/__init___.py
esai/pipeline/data/filetohtml.py
esai/pipeline/data/htmltomd.py
esai/pipeline/data/segmentation.py
esai/pipeline/data/tabular.py
esai/pipeline/data/textractor.py
esai/util/__init__.py
esai/util/resolver.py
esai-0.1.1.dist-info/licenses/LICENSE
esai-0.1.1.dist-info/METADATA
esai-0.1.1.dist-info/WHEEL
esai-0.1.1.dist-info/top_level.txt
esai-0.1.1.dist-info/RECORD
