Metadata-Version: 2.4
Name: esai
Version: 0.1.1
Summary: Practice backend framework for scalable text extraction
Author-email: Logidhasan <logidahasan454@gmail.com>
License: MIT
Requires-Python: >=3.8
License-File: LICENSE
Requires-Dist: PyYAML
Dynamic: license-file
